Radisys90-1.0.1.dist-info/DESCRIPTION.rst
Radisys90-1.0.1.dist-info/METADATA
Radisys90-1.0.1.dist-info/RECORD
Radisys90-1.0.1.dist-info/WHEEL
Radisys90-1.0.1.dist-info/metadata.json
Radisys90-1.0.1.dist-info/top_level.txt
jio_sonar/__init__.py
jio_sonar/gaia_arguments.py
jio_sonar/runner.py
jio_sonar/version.py
jio_sonar/device/__init__.py
jio_sonar/device/adb.py
jio_sonar/device/adb_b2g.py
jio_sonar/device/adbmanager.py
jio_sonar/device/errors.py
jio_sonar/device/version.py
jio_sonar/logi/__init__.py
jio_sonar/logi/commandline.py
jio_sonar/logi/logtypes.py
jio_sonar/logi/reader.py
jio_sonar/logi/structuredlog.py
jio_sonar/logi/unstructuredlog.py
jio_sonar/logi/formatters/__init__.py
jio_sonar/logi/formatters/base.py
jio_sonar/logi/formatters/machformatter.py
jio_sonar/logi/formatters/process.py
jio_sonar/logi/formatters/tbplformatter.py
jio_sonar/logi/formatters/unittest.py
jio_sonar/logi/formatters/xunit.py
jio_sonar/logi/formatters/html/__init__.py
jio_sonar/logi/formatters/html/html.py
jio_sonar/logi/formatters/html/xmlgen.py
jio_sonar/logi/handlers/__init__.py
jio_sonar/logi/handlers/base.py
jio_sonar/logi/handlers/bufferhandler.py
jio_sonar/marionette_driver/__init__.py
jio_sonar/marionette_driver/addons.py
jio_sonar/marionette_driver/by.py
jio_sonar/marionette_driver/date_time_value.py
jio_sonar/marionette_driver/decorators.py
jio_sonar/marionette_driver/errors.py
jio_sonar/marionette_driver/expected.py
jio_sonar/marionette_driver/geckoinstance.py
jio_sonar/marionette_driver/httpd.py
jio_sonar/marionette_driver/keys.py
jio_sonar/marionette_driver/localization.py
jio_sonar/marionette_driver/marionette.py
jio_sonar/marionette_driver/timeout.py
jio_sonar/marionette_driver/transport.py
jio_sonar/marionette_driver/wait.py
jio_sonar/mozprocess/__init__.py
jio_sonar/mozprocess/processhandler.py
jio_sonar/mozprocess/qijo.py
jio_sonar/mozprocess/winprocess.py
jio_sonar/test/__init__.py
jio_sonar/test/case.py
jio_sonar/test/results.py
