Metadata-Version: 2.0
Name: Radisys90
Version: 1.0.1
Summary: marionette
Home-page: UNKNOWN
Author: shayan
Author-email: syedshayan109@gmail.com
License: MIT
Download-URL: https://pypi.org/project/radisys90/
Keywords: radisys90,r90
Platform: UNKNOWN
Requires-Dist: mozrunner (==8.3.0)
Requires-Dist: mozversion (==2.4.0)
Requires-Dist: six (==1.16.0)
Requires-Dist: future (==0.18.3)
Requires-Dist: manifestparser (==2.1.0)
